cappa/__init__.py
cappa/arg.py
cappa/argparse.py
cappa/base.py
cappa/class_inspect.py
cappa/command.py
cappa/default.py
cappa/destructure.py
cappa/docstring.py
cappa/file_io.py
cappa/help.py
cappa/invoke.py
cappa/output.py
cappa/parse.py
cappa/parser.py
cappa/py.typed
cappa/state.py
cappa/subcommand.py
cappa/testing.py
cappa/themes.py
cappa/type_view.py
cappa/typing.py
cappa/completion/__init__.py
cappa/completion/base.py
cappa/completion/completers.py
cappa/completion/shells.py
cappa/completion/types.py
cappa/ext/__init__.py
cappa/ext/docutils.py
cappa-0.31.0.dist-info/METADATA
cappa-0.31.0.dist-info/WHEEL
cappa-0.31.0.dist-info/licenses/LICENSE
cappa-0.31.0.dist-info/RECORD
