Metadata-Version: 2.4
Name: cappa
Version: 0.31.0
Summary: Declarative CLI argument parser.
Project-URL: repository, https://github.com/dancardin/cappa
Author-email: Dan Cardin <ddcardin@gmail.com>
License:                                  Apache License
License-File: LICENSE
Keywords: CLI,argparse,click,parser,typer
Classifier: Topic :: Software Development :: Libraries :: Python Modules
Requires-Python: <4,>=3.8
Requires-Dist: rich>=12.1.0
Requires-Dist: type-lens>=0.2.5
Requires-Dist: typing-extensions>=4.12.0; python_version >= '3.13'
Requires-Dist: typing-extensions>=4.8.0
Provides-Extra: docstring
Requires-Dist: docstring-parser>=0.15; extra == 'docstring'
Requires-Dist: docstring-parser>=0.17; (python_version >= '3.14') and extra == 'docstring'
